python_jsonschema_objects/__init__.py
python_jsonschema_objects/_version.py
python_jsonschema_objects/classbuilder.py
python_jsonschema_objects/descriptors.py
python_jsonschema_objects/literals.py
python_jsonschema_objects/markdown_support.py
python_jsonschema_objects/pattern_properties.py
python_jsonschema_objects/util.py
python_jsonschema_objects/validators.py
python_jsonschema_objects/wrapper_types.py
python_jsonschema_objects/examples/README.md
python_jsonschema_objects/examples/__init__.py
python_jsonschema_objects-0.5.7.dist-info/LICENSE
python_jsonschema_objects-0.5.7.dist-info/METADATA
python_jsonschema_objects-0.5.7.dist-info/WHEEL
python_jsonschema_objects-0.5.7.dist-info/top_level.txt
python_jsonschema_objects-0.5.7.dist-info/RECORD
